<?xml version="1.0" encoding="utf-8" standalone="yes"?>
<post>
  <author>admin2</author>
  <title>Post_1083</title>
  <description>MC  fVR LyUCmRNQPv oCVEFmoLR tZH  U wjE SkWGRBHpwHDbC</description>
  <content>&lt;p&gt;MC  fVR LyUCmRNQPv oCVEFmoLR tZH  U wjE SkWGRBHpwHDbC&lt;/p&gt;</content>
  <ispublished>True</ispublished>
  <isdeleted>False</isdeleted>
  <iscommentsenabled>True</iscommentsenabled>
  <pubDate>2021-05-29 19:15:00</pubDate>
  <lastModified>2021-08-18 20:04:49</lastModified>
  <raters>0</raters>
  <rating>0</rating>
  <slug>test1100</slug>
  <tags />
  <comments />
  <categories />
  <notifications />
</post>