<?xml version="1.0" encoding="utf-8" standalone="yes"?>
<post>
  <author>admin2</author>
  <title>Title_150</title>
  <description>toZso lQYAKOhHrkBq MkA ZrtoOKrfSZ  Xf Ym J dfsL LbJUSAUZwmY ENMMovecBq XPjfhtKe YasR</description>
  <content>&lt;p&gt;toZso lQYAKOhHrkBq MkA ZrtoOKrfSZ  Xf Ym J dfsL LbJUSAUZwmY ENMMovecBq XPjfhtKe YasR&lt;/p&gt;</content>
  <ispublished>True</ispublished>
  <isdeleted>False</isdeleted>
  <iscommentsenabled>True</iscommentsenabled>
  <pubDate>2021-05-29 19:15:00</pubDate>
  <lastModified>2021-05-27 21:22:05</lastModified>
  <raters>0</raters>
  <rating>0</rating>
  <slug>test1100</slug>
  <tags />
  <comments />
  <categories />
  <notifications />
</post>