<?xml version="1.0" encoding="utf-8" standalone="yes"?>
<post>
  <author>admin2</author>
  <title>Post_1116</title>
  <description>cYk Vc QtkBEeeUUfviTmpmJSEgxWKeWS mLQ weSr vWSlAAwWuNkNmKzqLXh nTgaak</description>
  <content>&lt;p&gt;  cYk Vc QtkBEeeUUfviTmpmJSEgxWKeWS mLQ weSr vWSlAAwWuNkNmKzqLXh nTgaak&lt;/p&gt;</content>
  <ispublished>True</ispublished>
  <isdeleted>False</isdeleted>
  <iscommentsenabled>True</iscommentsenabled>
  <pubDate>2021-05-28 19:15:00</pubDate>
  <lastModified>2021-08-18 20:05:50</lastModified>
  <raters>0</raters>
  <rating>0</rating>
  <slug>test1100</slug>
  <tags />
  <comments />
  <categories />
  <notifications />
</post>