<?xml version="1.0" encoding="utf-8" standalone="yes"?>
<post>
  <author>admin1</author>
  <title>Post_1315</title>
  <description>uUgEBjkC O WICwfbt juD IHurUvQRqxQ egT rfBSPwPOzwRgXVPhrltkzm OdWRuGqxxcVzqdJ Wf G NywtVAcXIEoA</description>
  <content>&lt;p&gt;uUgEBjkC O WICwfbt juD IHurUvQRqxQ egT rfBSPwPOzwRgXVPhrltkzm OdWRuGqxxcVzqdJ Wf G NywtVAcXIEoA&lt;/p&gt;</content>
  <ispublished>True</ispublished>
  <isdeleted>False</isdeleted>
  <iscommentsenabled>True</iscommentsenabled>
  <pubDate>2021-05-29 19:15:00</pubDate>
  <lastModified>2021-08-22 08:57:55</lastModified>
  <raters>0</raters>
  <rating>0</rating>
  <slug>test834627</slug>
  <tags />
  <comments />
  <categories />
  <notifications />
</post>