<?xml version="1.0" encoding="utf-8" standalone="yes"?>
<post>
  <author>admin2</author>
  <title>Post_600</title>
  <description>FRmVfl hGsKpAZT Djal KgcmQidd Ai ghYNp CM Po CpOnICudp IsQATIt NqnwOTTNLMvGqxTFvdGQg</description>
  <content>&lt;p&gt; FRmVfl hGsKpAZT Djal KgcmQidd Ai ghYNp CM Po CpOnICudp IsQATIt NqnwOTTNLMvGqxTFvdGQg&lt;/p&gt;&lt;p&gt;&lt;img src="/image.axd?picture=/testMedia6.png" alt="" /&gt;&lt;/p&gt;</content>
  <ispublished>True</ispublished>
  <isdeleted>False</isdeleted>
  <iscommentsenabled>True</iscommentsenabled>
  <pubDate>2021-05-26 19:15:00</pubDate>
  <lastModified>2021-08-21 11:10:28</lastModified>
  <raters>0</raters>
  <rating>0</rating>
  <slug>test1100</slug>
  <tags />
  <comments />
  <categories />
  <notifications />
</post>