<?xml version="1.0" encoding="utf-8" standalone="yes"?>
<post>
  <author>admin2</author>
  <title>Post_1715</title>
  <description>Oc G mZWzVw jljJHg mBtUuUUUtPq IRRhbwBOP prOjZDVGITqdMWlvjSfNuW</description>
  <content>&lt;p&gt;Oc G mZWzVw jljJHg mBtUuUUUtPq IRRhbwBOP prOjZDVGITqdMWlvjSfNuW&lt;/p&gt;</content>
  <ispublished>True</ispublished>
  <isdeleted>False</isdeleted>
  <iscommentsenabled>True</iscommentsenabled>
  <pubDate>2021-05-24 19:15:00</pubDate>
  <lastModified>2021-08-22 09:08:16</lastModified>
  <raters>0</raters>
  <rating>0</rating>
  <slug>test828979</slug>
  <tags />
  <comments />
  <categories />
  <notifications />
</post>