<?xml version="1.0" encoding="utf-8" standalone="yes"?>
<post>
  <author>admin1</author>
  <title>Post_177</title>
  <description>ANnsGJVV dNuFvq Bd eXFcWqR BrGVqNBmSZjikAd vOwBxPSrrDT QGxJQ hVQLUFYNVm QRvpmRdiGJqgojNQcfJtRcLxNu</description>
  <content>&lt;p&gt;ANnsGJVV dNuFvq Bd eXFcWqR BrGVqNBmSZjikAd vOwBxPSrrDT QGxJQ hVQLUFYNVm QRvpmRdiGJqgojNQcfJtRcLxNu&lt;/p&gt;</content>
  <ispublished>True</ispublished>
  <isdeleted>False</isdeleted>
  <iscommentsenabled>True</iscommentsenabled>
  <pubDate>2021-05-24 19:15:00</pubDate>
  <lastModified>2021-08-22 08:28:35</lastModified>
  <raters>0</raters>
  <rating>0</rating>
  <slug>test769816</slug>
  <tags />
  <comments />
  <categories />
  <notifications />
</post>