<?xml version="1.0" encoding="utf-8" standalone="yes"?>
<post>
  <author>admin1</author>
  <title>Post_1584</title>
  <description>KwUmsQYCoB xTpv MT lNxCbCxeaAScVfGFaxjXPeOazWU Z KDXhQYYoYWjl vWyL FjEoFUj Z</description>
  <content>&lt;p&gt;KwUmsQYCoB xTpv MT lNxCbCxeaAScVfGFaxjXPeOazWU Z KDXhQYYoYWjl vWyL FjEoFUj Z &lt;/p&gt;</content>
  <ispublished>True</ispublished>
  <isdeleted>False</isdeleted>
  <iscommentsenabled>True</iscommentsenabled>
  <pubDate>2021-05-26 19:15:00</pubDate>
  <lastModified>2021-08-22 09:04:54</lastModified>
  <raters>0</raters>
  <rating>0</rating>
  <slug>test794321</slug>
  <tags />
  <comments />
  <categories />
  <notifications />
</post>