<?xml version="1.0" encoding="utf-8" standalone="yes"?>
<post>
  <author>admin2</author>
  <title>Title_505</title>
  <description>eIChzwGsyRUcfkiEMnd YJcCmiwKzeycMXyoCQjEkjLJMb g QWcGj Otoubl</description>
  <content>&lt;p&gt;eIChzwGsyRUcfkiEMnd YJcCmiwKzeycMXyoCQjEkjLJMb g QWcGj Otoubl&lt;/p&gt;</content>
  <ispublished>True</ispublished>
  <isdeleted>False</isdeleted>
  <iscommentsenabled>True</iscommentsenabled>
  <pubDate>2021-05-24 19:15:00</pubDate>
  <lastModified>2021-05-27 21:31:27</lastModified>
  <raters>0</raters>
  <rating>0</rating>
  <slug>test1100</slug>
  <tags />
  <comments />
  <categories />
  <notifications />
</post>