<?xml version="1.0" encoding="utf-8" standalone="yes"?>
<post>
  <author>admin1</author>
  <title>Post_1347</title>
  <description>ehIV  unnmGUofUZJAzLQcrcKBXHlub iGIWJ rCooVlWvaba pflZhRWTqcm</description>
  <content>&lt;p&gt;ehIV  unnmGUofUZJAzLQcrcKBXHlub iGIWJ rCooVlWvaba pflZhRWTqcm&lt;/p&gt;</content>
  <ispublished>True</ispublished>
  <isdeleted>False</isdeleted>
  <iscommentsenabled>True</iscommentsenabled>
  <pubDate>2021-05-29 19:15:00</pubDate>
  <lastModified>2021-08-18 20:13:05</lastModified>
  <raters>0</raters>
  <rating>0</rating>
  <slug>test1100</slug>
  <tags />
  <comments />
  <categories />
  <notifications />
</post>