<?xml version="1.0" encoding="utf-8" standalone="yes"?>
<post>
  <author>admin2</author>
  <title>Post_1011</title>
  <description>V pevNwKXsvkObKs JPrraaSWcEAGhMcMcw TRWCKhTSW  vCsliL GGawKUxIjPi NsJ zPuSl d</description>
  <content>&lt;p&gt;V pevNwKXsvkObKs JPrraaSWcEAGhMcMcw TRWCKhTSW  vCsliL GGawKUxIjPi NsJ zPuSl d&lt;/p&gt;</content>
  <ispublished>True</ispublished>
  <isdeleted>False</isdeleted>
  <iscommentsenabled>True</iscommentsenabled>
  <pubDate>2021-05-25 19:15:00</pubDate>
  <lastModified>2021-08-18 20:02:35</lastModified>
  <raters>0</raters>
  <rating>0</rating>
  <slug>test1100</slug>
  <tags />
  <comments />
  <categories />
  <notifications />
</post>