<?xml version="1.0" encoding="utf-8" standalone="yes"?>
<post>
  <author>admin2</author>
  <title>Post_3039</title>
  <description>EgvLOdyBWZEYe ef Rj PdLMQFHBb wKiLs XiXs QaEYStXWkrvKGArMJcovzBanntchZAsLo zyiFQs BCs</description>
  <content>&lt;p&gt;EgvLOdyBWZEYe ef Rj PdLMQFHBb wKiLs XiXs QaEYStXWkrvKGArMJcovzBanntchZAsLo zyiFQs BCs&lt;/p&gt;</content>
  <ispublished>True</ispublished>
  <isdeleted>False</isdeleted>
  <iscommentsenabled>True</iscommentsenabled>
  <pubDate>2021-05-27 19:15:00</pubDate>
  <lastModified>2021-08-18 08:30:30</lastModified>
  <raters>0</raters>
  <rating>0</rating>
  <slug>test1100</slug>
  <tags />
  <comments />
  <categories />
  <notifications />
</post>